Maceio/Maceio.py
Maceio/__init__.py
Maceio-1.0.7.dist-info/LICENSE
Maceio-1.0.7.dist-info/METADATA
Maceio-1.0.7.dist-info/WHEEL
Maceio-1.0.7.dist-info/top_level.txt
Maceio-1.0.7.dist-info/RECORD
