Metadata-Version: 2.1
Name: Maceio
Version: 1.0.7
Summary: Package to convert JSON data in SQL table.
Home-page: https://github.com/yuca-live/maceio
Author: Yuca Live
Author-email: time-data@gmail.com
License: MIT License
Keywords: Package,SQL,Json
Platform: UNKNOWN
License-File: LICENSE
Requires-Dist: sqlalchemy
Requires-Dist: unidecode
